synthetic_image_analyzer/__init__.py
synthetic_image_analyzer/extract_features.py
synthetic_image_analyzer/fid_score.py
synthetic_image_analyzer/image_dataset.py
synthetic_image_analyzer/main.py
synthetic_image_analyzer/quality_evaluator.py
synthetic_image_analyzer/train.py
synthetic_image_analyzer/utils.py
synthetic_image_analyzer/vqvae.py
synthetic_image_analyzer-1.0.0.dist-info/METADATA
synthetic_image_analyzer-1.0.0.dist-info/WHEEL
synthetic_image_analyzer-1.0.0.dist-info/entry_points.txt
synthetic_image_analyzer-1.0.0.dist-info/top_level.txt
synthetic_image_analyzer-1.0.0.dist-info/RECORD
